django_rholang_editor/__init__.py
django_rholang_editor/fields.py
django_rholang_editor/widgets.py
django_rholang_editor/static/rhoeditor/rhoeditor/ace.js
django_rholang_editor/static/rhoeditor/rhoeditor/ext-beautify.js
django_rholang_editor/static/rhoeditor/rhoeditor/ext-elastic_tabstops_lite.js
django_rholang_editor/static/rhoeditor/rhoeditor/ext-emmet.js
django_rholang_editor/static/rhoeditor/rhoeditor/ext-error_marker.js
django_rholang_editor/static/rhoeditor/rhoeditor/ext-keybinding_menu.js
django_rholang_editor/static/rhoeditor/rhoeditor/ext-language_tools.js
django_rholang_editor/static/rhoeditor/rhoeditor/ext-linking.js
django_rholang_editor/static/rhoeditor/rhoeditor/ext-modelist.js
django_rholang_editor/static/rhoeditor/rhoeditor/ext-options.js
django_rholang_editor/static/rhoeditor/rhoeditor/ext-searchbox.js
django_rholang_editor/static/rhoeditor/rhoeditor/ext-settings_menu.js
django_rholang_editor/static/rhoeditor/rhoeditor/ext-spellcheck.js
django_rholang_editor/static/rhoeditor/rhoeditor/ext-split.js
django_rholang_editor/static/rhoeditor/rhoeditor/ext-static_highlight.js
django_rholang_editor/static/rhoeditor/rhoeditor/ext-statusbar.js
django_rholang_editor/static/rhoeditor/rhoeditor/ext-textarea.js
django_rholang_editor/static/rhoeditor/rhoeditor/ext-themelist.js
django_rholang_editor/static/rhoeditor/rhoeditor/ext-whitespace.js
django_rholang_editor/static/rhoeditor/rhoeditor/keybinding-emacs.js
django_rholang_editor/static/rhoeditor/rhoeditor/keybinding-vim.js
django_rholang_editor/static/rhoeditor/rhoeditor/mode-rholang.js
django_rholang_editor/static/rhoeditor/rhoeditor/theme-ambiance.js
django_rholang_editor/static/rhoeditor/rhoeditor/theme-chaos.js
django_rholang_editor/static/rhoeditor/rhoeditor/theme-chrome.js
django_rholang_editor/static/rhoeditor/rhoeditor/theme-clouds.js
django_rholang_editor/static/rhoeditor/rhoeditor/theme-clouds_midnight.js
django_rholang_editor/static/rhoeditor/rhoeditor/theme-cobalt.js
django_rholang_editor-0.1.2.dist-info/DESCRIPTION.rst
django_rholang_editor-0.1.2.dist-info/METADATA
django_rholang_editor-0.1.2.dist-info/RECORD
django_rholang_editor-0.1.2.dist-info/WHEEL
django_rholang_editor-0.1.2.dist-info/metadata.json
django_rholang_editor-0.1.2.dist-info/top_level.txt
