Metadata-Version: 2.0
Name: django-rholang-editor
Version: 0.1.2
Summary: django rholang editor app based on ace editor
Home-page: https://github.com/zsluedem/django-rholang-editor
Author: zsluedem
Author-email: zsluedem06@gmail.com
License: Simplified BSD
Keywords: rholang
Platform: UNKNOWN
Classifier: Development Status :: 4 - Beta
Classifier: Environment :: Web Environment
Classifier: Intended Audience :: Developers
Classifier: License :: OSI Approved :: BSD License
Classifier: Operating System :: OS Independent
Classifier: Programming Language :: Python
Classifier: Framework :: Django
Requires-Dist: Django
Requires-Dist: django-js-asset (==1.0.0)
